.gitignore
.readthedocs.yml
.travis.yml
CHANGELOG.rst
LICENSE
MANIFEST.in
README.rst
setup.cfg
setup.py
tox.ini
src/tendril/__init__.py
src/tendril/apiserver/__init__.py
src/tendril/apiserver/core.py
src/tendril/apiserver/server.py
src/tendril/apiserver/exceptions/__init__.py
src/tendril/apiserver/exceptions/common.py
src/tendril/apiserver/routers/__init__.py
src/tendril/apiserver/routers/diagnostics.py
src/tendril/apiserver/routers/system.py
src/tendril/authz/__init__.py
src/tendril/authz/scopes/__init__.py
src/tendril/authz/scopes/system.py
src/tendril/common/__init__.py
src/tendril/common/exceptions.py
src/tendril/config/__init__.py
src/tendril/config/server.py
src/tendril/resources/test_certificate.pem
src/tendril/resources/test_key.pem
src/tendril_apiserver_core.egg-info/PKG-INFO
src/tendril_apiserver_core.egg-info/SOURCES.txt
src/tendril_apiserver_core.egg-info/dependency_links.txt
src/tendril_apiserver_core.egg-info/entry_points.txt
src/tendril_apiserver_core.egg-info/requires.txt
src/tendril_apiserver_core.egg-info/top_level.txt